{"orders":[{"id":"c16e67ac-d380-42e4-9b6f-53fa5111e28e","externalId":"1C-009","orderNumber":"ЗН-2026-0309","scheduledTime":"2026-03-23T08:44:24.273Z","status":"scheduled","plateNumber":"unknown","workType":"ТО-1","normHours":2,"actualHours":null,"createdAt":"2026-03-23T06:44:24.803Z","updatedAt":"2026-03-23T06:44:24.803Z","links":[]},{"id":"2d0e3f4c-9f2c-4369-8202-d342eec9bd3d","externalId":"1C-008","orderNumber":"ЗН-2026-0308","scheduledTime":"2026-03-23T07:44:24.273Z","status":"scheduled","plateNumber":"Р333УУ77","workType":"Шиномонтаж","normHours":1,"actualHours":null,"createdAt":"2026-03-23T06:44:24.796Z","updatedAt":"2026-03-23T06:44:24.796Z","links":[]},{"id":"105724ef-435f-4d32-938b-152ff413b6b9","externalId":"1C-007","orderNumber":"ЗН-2026-0307","scheduledTime":"2026-03-23T06:14:24.273Z","status":"in_progress","plateNumber":"О222НН50","workType":"Компьютерная диагностика","normHours":0.5,"actualHours":null,"createdAt":"2026-03-23T06:44:24.791Z","updatedAt":"2026-03-23T06:44:24.791Z","links":[{"id":"6b36bf09-5e3c-4058-9a39-9036ab09d3ac","vehicleSessionId":"deda8ea6-8df4-47cd-bdd1-9106e84003ce","postStayId":null,"workOrderId":"105724ef-435f-4d32-938b-152ff413b6b9","confidence":0.8844185172822286,"matchType":"plate","vehicleSession":{"id":"deda8ea6-8df4-47cd-bdd1-9106e84003ce","plateNumber":"О222НН50","entryTime":"2026-03-23T05:02:24.273Z","exitTime":null,"status":"active","trackId":"track_7","createdAt":"2026-03-23T06:44:24.605Z","updatedAt":"2026-03-23T06:44:24.605Z"},"postStay":null}]},{"id":"402a6aa3-7714-469f-9e41-b673d65cf6d0","externalId":"1C-004","orderNumber":"ЗН-2026-0304","scheduledTime":"2026-03-23T05:44:24.273Z","status":"in_progress","plateNumber":"Х999ХХ77","workType":"Диагностика двигателя","normHours":2,"actualHours":null,"createdAt":"2026-03-23T06:44:24.775Z","updatedAt":"2026-03-23T06:44:24.775Z","links":[{"id":"592fe077-6bdb-489a-8660-55f2476ecb8c","vehicleSessionId":"0255fcec-51a2-4265-a035-4867a3236efd","postStayId":null,"workOrderId":"402a6aa3-7714-469f-9e41-b673d65cf6d0","confidence":0.990409650007196,"matchType":"plate","vehicleSession":{"id":"0255fcec-51a2-4265-a035-4867a3236efd","plateNumber":"Х999ХХ77","entryTime":"2026-03-23T04:08:24.273Z","exitTime":null,"status":"active","trackId":"track_4","createdAt":"2026-03-23T06:44:24.590Z","updatedAt":"2026-03-23T06:44:24.590Z"},"postStay":null}]},{"id":"f1467d60-93a3-42a4-8287-0a0eb2f42eb7","externalId":"1C-006","orderNumber":"ЗН-2026-0306","scheduledTime":"2026-03-23T05:32:24.273Z","status":"in_progress","plateNumber":"К111АА99","workType":"Замена масла + фильтры","normHours":1,"actualHours":null,"createdAt":"2026-03-23T06:44:24.786Z","updatedAt":"2026-03-23T06:44:24.786Z","links":[{"id":"bc84615f-e79d-4fd9-9c85-9ffb5eb77359","vehicleSessionId":"9e4a85c1-c70f-4018-95d2-944e9edea590","postStayId":null,"workOrderId":"f1467d60-93a3-42a4-8287-0a0eb2f42eb7","confidence":0.8883663028098794,"matchType":"plate","vehicleSession":{"id":"9e4a85c1-c70f-4018-95d2-944e9edea590","plateNumber":"К111АА99","entryTime":"2026-03-23T04:44:24.273Z","exitTime":null,"status":"active","trackId":"track_6","createdAt":"2026-03-23T06:44:24.600Z","updatedAt":"2026-03-23T06:44:24.600Z"},"postStay":null}]},{"id":"b93c6910-eeb1-4df3-8d68-05d9e5e45f44","externalId":"1C-003","orderNumber":"ЗН-2026-0303","scheduledTime":"2026-03-23T05:14:24.273Z","status":"in_progress","plateNumber":"Е789ОР77","workType":"Диагностика ходовой","normHours":1,"actualHours":null,"createdAt":"2026-03-23T06:44:24.770Z","updatedAt":"2026-03-23T06:44:24.770Z","links":[{"id":"62588338-d85a-499a-9907-76a98bc201bf","vehicleSessionId":"668feeae-4f50-4274-9749-05b8e080deb6","postStayId":null,"workOrderId":"b93c6910-eeb1-4df3-8d68-05d9e5e45f44","confidence":0.9745712866683032,"matchType":"plate","vehicleSession":{"id":"668feeae-4f50-4274-9749-05b8e080deb6","plateNumber":"Е789ОР77","entryTime":"2026-03-23T03:50:24.273Z","exitTime":null,"status":"active","trackId":"track_3","createdAt":"2026-03-23T06:44:24.584Z","updatedAt":"2026-03-23T06:44:24.584Z"},"postStay":null}]},{"id":"18f6f4ff-6c64-45ef-8d33-9d2b8d971b38","externalId":"1C-005","orderNumber":"ЗН-2026-0305","scheduledTime":"2026-03-23T04:56:24.273Z","status":"in_progress","plateNumber":"М777ММ97","workType":"Замена стоек","normHours":2.5,"actualHours":null,"createdAt":"2026-03-23T06:44:24.781Z","updatedAt":"2026-03-23T06:44:24.781Z","links":[{"id":"ac155bd8-9240-434c-837e-4703ef94f669","vehicleSessionId":"0a6acc1e-2996-4975-b61b-0a7563ab69ad","postStayId":null,"workOrderId":"18f6f4ff-6c64-45ef-8d33-9d2b8d971b38","confidence":0.9277942851183473,"matchType":"plate","vehicleSession":{"id":"0a6acc1e-2996-4975-b61b-0a7563ab69ad","plateNumber":"М777ММ97","entryTime":"2026-03-23T04:26:24.273Z","exitTime":null,"status":"active","trackId":"track_5","createdAt":"2026-03-23T06:44:24.595Z","updatedAt":"2026-03-23T06:44:24.595Z"},"postStay":null}]},{"id":"50c7deac-a06d-4f4a-84ad-9739a3440cf8","externalId":"1C-002","orderNumber":"ЗН-2026-0302","scheduledTime":"2026-03-23T04:14:24.273Z","status":"in_progress","plateNumber":"В456КМ50","workType":"Замена тормозных колодок","normHours":1.5,"actualHours":null,"createdAt":"2026-03-23T06:44:24.766Z","updatedAt":"2026-03-23T06:44:24.766Z","links":[{"id":"3822c6f9-5d1c-4ad6-82bb-9ba46abfe6b0","vehicleSessionId":"40f5513d-b6cf-436b-bba9-dccfdd247ea9","postStayId":null,"workOrderId":"50c7deac-a06d-4f4a-84ad-9739a3440cf8","confidence":0.9966730056741607,"matchType":"plate","vehicleSession":{"id":"40f5513d-b6cf-436b-bba9-dccfdd247ea9","plateNumber":"В456КМ50","entryTime":"2026-03-23T03:32:24.273Z","exitTime":null,"status":"active","trackId":"track_2","createdAt":"2026-03-23T06:44:24.579Z","updatedAt":"2026-03-23T06:44:24.579Z"},"postStay":null}]},{"id":"fc4cfc64-b977-4058-8cd2-d053b6b2feea","externalId":"1C-001","orderNumber":"ЗН-2026-0301","scheduledTime":"2026-03-23T03:44:24.273Z","status":"in_progress","plateNumber":"А123ВС77","workType":"ТО-2","normHours":3,"actualHours":2.3,"createdAt":"2026-03-23T06:44:24.760Z","updatedAt":"2026-03-23T06:44:24.760Z","links":[{"id":"f325593d-ccd0-4c8a-96ea-ffcf8a97c361","vehicleSessionId":"d6c71d3d-fcfc-4db4-9150-d7e3ab69cc3f","postStayId":null,"workOrderId":"fc4cfc64-b977-4058-8cd2-d053b6b2feea","confidence":0.9116728316758388,"matchType":"plate","vehicleSession":{"id":"d6c71d3d-fcfc-4db4-9150-d7e3ab69cc3f","plateNumber":"А123ВС77","entryTime":"2026-03-23T03:14:24.273Z","exitTime":null,"status":"active","trackId":"track_1","createdAt":"2026-03-23T06:44:24.572Z","updatedAt":"2026-03-23T06:44:24.572Z"},"postStay":null}]},{"id":"1cd34db7-789a-45ff-97b2-9add375a36b4","externalId":"1C-010","orderNumber":"ЗН-2026-0310","scheduledTime":"2026-03-23T01:44:24.273Z","status":"no_show","plateNumber":"АВ55577","workType":"Замена сцепления","normHours":4,"actualHours":null,"createdAt":"2026-03-23T06:44:24.807Z","updatedAt":"2026-03-23T06:44:24.807Z","links":[]},{"id":"a140d3d5-c0aa-47e5-8070-a8033bdfef53","externalId":"1C-011","orderNumber":"ЗН-2026-0311","scheduledTime":"2026-03-22T23:44:24.273Z","status":"completed","plateNumber":"АМ97745","workType":"Замена ремня ГРМ","normHours":3.5,"actualHours":3.2,"createdAt":"2026-03-23T06:44:24.811Z","updatedAt":"2026-03-23T06:44:24.811Z","links":[]},{"id":"ac4079cb-8677-420c-9fd3-dfe50a3bb74c","externalId":"1C-012","orderNumber":"ЗН-2026-0312","scheduledTime":"2026-03-22T22:44:24.273Z","status":"completed","plateNumber":"ВН12377","workType":"Покраска бампера","normHours":6,"actualHours":5.5,"createdAt":"2026-03-23T06:44:24.815Z","updatedAt":"2026-03-23T06:44:24.815Z","links":[]}],"total":12}