[{"id":"5767d027-c333-4f4f-9d0e-7182603270e2","zoneId":"1fb7f017-1ba1-47e0-a2e2-5982481d6303","name":"Пост 1","type":"light","status":"active_work","coordinates":null,"isActive":true,"createdAt":"2026-03-21T20:01:43.565Z","updatedAt":"2026-03-21T20:01:43.565Z","zone":{"id":"1fb7f017-1ba1-47e0-a2e2-5982481d6303","name":"Ремонтная зона (посты 1-4)","type":"repair","description":"Нижний ряд, 2-х стоечные подъёмники","coordinates":null,"isActive":true,"createdAt":"2026-03-21T20:01:43.522Z","updatedAt":"2026-03-21T20:01:43.522Z"},"stays":[{"id":"30754d1c-ddc1-48a9-90b7-30345d5d2d79","postId":"5767d027-c333-4f4f-9d0e-7182603270e2","vehicleSessionId":"ebbd6005-52de-49b5-bdab-7c3a84529b78","startTime":"2026-03-21T17:43:43.442Z","endTime":null,"hasWorker":true,"isActive":true,"activeTime":7200,"idleTime":600,"vehicleSession":{"id":"ebbd6005-52de-49b5-bdab-7c3a84529b78","plateNumber":"А123ВС77","entryTime":"2026-03-21T16:31:43.442Z","exitTime":null,"status":"active","trackId":"track_1","createdAt":"2026-03-21T20:01:43.740Z","updatedAt":"2026-03-21T20:01:43.740Z"}}]},{"id":"719be8f7-769a-4ed4-a23a-29fcaa7cb53e","zoneId":"b41cab2a-44f8-4455-8f91-29b28cd5a8fa","name":"Пост 10","type":"special","status":"free","coordinates":null,"isActive":true,"createdAt":"2026-03-21T20:01:43.587Z","updatedAt":"2026-03-21T20:01:43.587Z","zone":{"id":"b41cab2a-44f8-4455-8f91-29b28cd5a8fa","name":"Диагностика (посты 9-10)","type":"parking","description":"Правая часть СТО, диагностические посты","coordinates":null,"isActive":true,"createdAt":"2026-03-21T20:01:43.535Z","updatedAt":"2026-03-21T20:01:43.535Z"},"stays":[]},{"id":"f8626e9b-275f-4f6c-b1f9-73e65d8fb825","zoneId":"1fb7f017-1ba1-47e0-a2e2-5982481d6303","name":"Пост 2","type":"light","status":"occupied_no_work","coordinates":null,"isActive":true,"createdAt":"2026-03-21T20:01:43.570Z","updatedAt":"2026-03-21T20:01:43.570Z","zone":{"id":"1fb7f017-1ba1-47e0-a2e2-5982481d6303","name":"Ремонтная зона (посты 1-4)","type":"repair","description":"Нижний ряд, 2-х стоечные подъёмники","coordinates":null,"isActive":true,"createdAt":"2026-03-21T20:01:43.522Z","updatedAt":"2026-03-21T20:01:43.522Z"},"stays":[{"id":"df893c05-edc5-496e-8b5b-f2a824b1b94e","postId":"f8626e9b-275f-4f6c-b1f9-73e65d8fb825","vehicleSessionId":"b34cc36e-8b00-4d63-bf69-36cf711460d2","startTime":"2026-03-21T18:13:43.442Z","endTime":null,"hasWorker":false,"isActive":false,"activeTime":1800,"idleTime":4200,"vehicleSession":{"id":"b34cc36e-8b00-4d63-bf69-36cf711460d2","plateNumber":"В456КМ50","entryTime":"2026-03-21T16:49:43.442Z","exitTime":null,"status":"active","trackId":"track_2","createdAt":"2026-03-21T20:01:43.745Z","updatedAt":"2026-03-21T20:01:43.745Z"}}]},{"id":"ba93cdbb-561f-4cd6-91a0-128d27006c90","zoneId":"1fb7f017-1ba1-47e0-a2e2-5982481d6303","name":"Пост 3","type":"light","status":"active_work","coordinates":null,"isActive":true,"createdAt":"2026-03-21T20:01:43.574Z","updatedAt":"2026-03-21T20:01:43.574Z","zone":{"id":"1fb7f017-1ba1-47e0-a2e2-5982481d6303","name":"Ремонтная зона (посты 1-4)","type":"repair","description":"Нижний ряд, 2-х стоечные подъёмники","coordinates":null,"isActive":true,"createdAt":"2026-03-21T20:01:43.522Z","updatedAt":"2026-03-21T20:01:43.522Z"},"stays":[{"id":"441b4f4b-8ab2-4959-b7ff-1b53830d2bec","postId":"ba93cdbb-561f-4cd6-91a0-128d27006c90","vehicleSessionId":"bbf40e79-ca1f-4079-90b7-edd7b87bfee6","startTime":"2026-03-21T18:43:43.442Z","endTime":null,"hasWorker":true,"isActive":true,"activeTime":4200,"idleTime":300,"vehicleSession":{"id":"bbf40e79-ca1f-4079-90b7-edd7b87bfee6","plateNumber":"Е789ОР77","entryTime":"2026-03-21T17:07:43.442Z","exitTime":null,"status":"active","trackId":"track_3","createdAt":"2026-03-21T20:01:43.750Z","updatedAt":"2026-03-21T20:01:43.750Z"}}]},{"id":"b3ddb785-69ed-49d3-853f-ccb4d1b64361","zoneId":"1fb7f017-1ba1-47e0-a2e2-5982481d6303","name":"Пост 4","type":"heavy","status":"occupied","coordinates":null,"isActive":true,"createdAt":"2026-03-21T20:01:43.566Z","updatedAt":"2026-03-21T20:01:43.566Z","zone":{"id":"1fb7f017-1ba1-47e0-a2e2-5982481d6303","name":"Ремонтная зона (посты 1-4)","type":"repair","description":"Нижний ряд, 2-х стоечные подъёмники","coordinates":null,"isActive":true,"createdAt":"2026-03-21T20:01:43.522Z","updatedAt":"2026-03-21T20:01:43.522Z"},"stays":[{"id":"7599b748-6c5d-4150-82f5-ca463f095356","postId":"b3ddb785-69ed-49d3-853f-ccb4d1b64361","vehicleSessionId":"0a9f061e-28e1-4188-b0e1-bdaef02d909b","startTime":"2026-03-21T19:13:43.442Z","endTime":null,"hasWorker":true,"isActive":false,"activeTime":900,"idleTime":1200,"vehicleSession":{"id":"0a9f061e-28e1-4188-b0e1-bdaef02d909b","plateNumber":"Х999ХХ77","entryTime":"2026-03-21T17:25:43.442Z","exitTime":null,"status":"active","trackId":"track_4","createdAt":"2026-03-21T20:01:43.754Z","updatedAt":"2026-03-21T20:01:43.754Z"}}]},{"id":"45c1bb82-6c4a-4291-9c67-f2264e460711","zoneId":"5c79ad1d-441c-4474-8fec-059c8fb37083","name":"Пост 5","type":"light","status":"active_work","coordinates":null,"isActive":true,"createdAt":"2026-03-21T20:01:43.591Z","updatedAt":"2026-03-21T20:01:43.591Z","zone":{"id":"5c79ad1d-441c-4474-8fec-059c8fb37083","name":"Ремонтная зона (посты 5-8)","type":"repair","description":"Верхний ряд, 2-х стоечные подъёмники","coordinates":null,"isActive":true,"createdAt":"2026-03-21T20:01:43.530Z","updatedAt":"2026-03-21T20:01:43.530Z"},"stays":[{"id":"50b1d6e7-1ed3-4403-bb67-99173ffc7a19","postId":"45c1bb82-6c4a-4291-9c67-f2264e460711","vehicleSessionId":"a89ab1ad-377e-459c-b60b-fb8a9e8057ef","startTime":"2026-03-21T18:31:43.442Z","endTime":null,"hasWorker":true,"isActive":true,"activeTime":5000,"idleTime":400,"vehicleSession":{"id":"a89ab1ad-377e-459c-b60b-fb8a9e8057ef","plateNumber":"М777ММ97","entryTime":"2026-03-21T17:43:43.442Z","exitTime":null,"status":"active","trackId":"track_5","createdAt":"2026-03-21T20:01:43.758Z","updatedAt":"2026-03-21T20:01:43.758Z"}}]},{"id":"8114ac40-f543-4773-ba17-822edf2a8b48","zoneId":"5c79ad1d-441c-4474-8fec-059c8fb37083","name":"Пост 6","type":"light","status":"free","coordinates":null,"isActive":true,"createdAt":"2026-03-21T20:01:43.597Z","updatedAt":"2026-03-21T20:01:43.597Z","zone":{"id":"5c79ad1d-441c-4474-8fec-059c8fb37083","name":"Ремонтная зона (посты 5-8)","type":"repair","description":"Верхний ряд, 2-х стоечные подъёмники","coordinates":null,"isActive":true,"createdAt":"2026-03-21T20:01:43.530Z","updatedAt":"2026-03-21T20:01:43.530Z"},"stays":[]},{"id":"3854da19-febd-4a56-b088-27a50d94c6f9","zoneId":"5c79ad1d-441c-4474-8fec-059c8fb37083","name":"Пост 7","type":"light","status":"occupied","coordinates":null,"isActive":true,"createdAt":"2026-03-21T20:01:43.602Z","updatedAt":"2026-03-21T20:01:43.602Z","zone":{"id":"5c79ad1d-441c-4474-8fec-059c8fb37083","name":"Ремонтная зона (посты 5-8)","type":"repair","description":"Верхний ряд, 2-х стоечные подъёмники","coordinates":null,"isActive":true,"createdAt":"2026-03-21T20:01:43.530Z","updatedAt":"2026-03-21T20:01:43.530Z"},"stays":[{"id":"04f6b51c-9d64-4f1e-b03f-dd2bef2329a7","postId":"3854da19-febd-4a56-b088-27a50d94c6f9","vehicleSessionId":"a9937aa5-ee55-4f5d-a2c0-67fe3abd2317","startTime":"2026-03-21T19:01:43.442Z","endTime":null,"hasWorker":true,"isActive":false,"activeTime":1200,"idleTime":2400,"vehicleSession":{"id":"a9937aa5-ee55-4f5d-a2c0-67fe3abd2317","plateNumber":"К111АА99","entryTime":"2026-03-21T18:01:43.442Z","exitTime":null,"status":"active","trackId":"track_6","createdAt":"2026-03-21T20:01:43.762Z","updatedAt":"2026-03-21T20:01:43.762Z"}}]},{"id":"53fcb505-556c-4198-8d76-4290b5779a40","zoneId":"5c79ad1d-441c-4474-8fec-059c8fb37083","name":"Пост 8","type":"light","status":"free","coordinates":null,"isActive":true,"createdAt":"2026-03-21T20:01:43.578Z","updatedAt":"2026-03-21T20:01:43.578Z","zone":{"id":"5c79ad1d-441c-4474-8fec-059c8fb37083","name":"Ремонтная зона (посты 5-8)","type":"repair","description":"Верхний ряд, 2-х стоечные подъёмники","coordinates":null,"isActive":true,"createdAt":"2026-03-21T20:01:43.530Z","updatedAt":"2026-03-21T20:01:43.530Z"},"stays":[]},{"id":"46ff6c4c-f4b9-428b-973d-c99f4a2d6a1f","zoneId":"b41cab2a-44f8-4455-8f91-29b28cd5a8fa","name":"Пост 9","type":"special","status":"active_work","coordinates":null,"isActive":true,"createdAt":"2026-03-21T20:01:43.583Z","updatedAt":"2026-03-21T20:01:43.583Z","zone":{"id":"b41cab2a-44f8-4455-8f91-29b28cd5a8fa","name":"Диагностика (посты 9-10)","type":"parking","description":"Правая часть СТО, диагностические посты","coordinates":null,"isActive":true,"createdAt":"2026-03-21T20:01:43.535Z","updatedAt":"2026-03-21T20:01:43.535Z"},"stays":[{"id":"a79e4b10-2203-48a3-951f-8ba683e66449","postId":"46ff6c4c-f4b9-428b-973d-c99f4a2d6a1f","vehicleSessionId":"93b2a532-c23a-450b-b0bc-ca20963fd667","startTime":"2026-03-21T19:31:43.442Z","endTime":null,"hasWorker":true,"isActive":true,"activeTime":1800,"idleTime":0,"vehicleSession":{"id":"93b2a532-c23a-450b-b0bc-ca20963fd667","plateNumber":"О222НН50","entryTime":"2026-03-21T18:19:43.442Z","exitTime":null,"status":"active","trackId":"track_7","createdAt":"2026-03-21T20:01:43.767Z","updatedAt":"2026-03-21T20:01:43.767Z"}}]}]